Metadata-Version: 2.1
Name: coelho
Version: 0.1
Summary: Candango Coelho AMPQ Toolkit
Home-page: https://github.com/candango/coelho
Author: Flavio Garcia
Author-email: piraz@candango.org
Maintainer: Flavio Garcia
Maintainer-email: piraz@candango.org
License: Apache License V2.0
Platform: UNKNOWN
Classifier: Development Status :: 2 - Pre-Alpha
Classifier: Environment :: Console
Classifier: Environment :: Web Environment
Classifier: License :: OSI Approved :: Apache Software License
Classifier: Operating System :: OS Independent
Classifier: Programming Language :: Python :: 3.5
Classifier: Programming Language :: Python :: 3.6
Classifier: Topic :: Internet :: WWW/HTTP
Classifier: Topic :: Internet :: WWW/HTTP :: Dynamic Content
Classifier: Topic :: Internet :: WWW/HTTP :: WSGI
Classifier: Topic :: Software Development :: Libraries :: Application Frameworks
Classifier: Topic :: Software Development :: Libraries :: Python Modules
